{
  "name": "catppuccin_latte",
  "highlights": {
    "attribute": {
      "fg": "#fe640b"
    },
    "attribute.builtin": {
      "fg": "#ea76cb"
    },
    "boolean": {
      "fg": "#fe640b"
    },
    "character": {
      "fg": "#179299"
    },
    "character.special": {
      "fg": "#ea76cb"
    },
    "comment": {
      "fg": "#7c7f93",
      "italic": true
    },
    "comment.documentation": {
      "fg": "#7c7f93",
      "italic": true
    },
    "comment.error": {
      "bg": "#d20f39",
      "fg": "#eff1f5"
    },
    "comment.note": {
      "bg": "#1e66f5",
      "fg": "#eff1f5"
    },
    "comment.todo": {
      "bg": "#dd7878",
      "fg": "#eff1f5"
    },
    "comment.warning": {
      "bg": "#df8e1d",
      "fg": "#eff1f5"
    },
    "constant": {
      "fg": "#fe640b"
    },
    "constant.builtin": {
      "fg": "#fe640b"
    },
    "constant.macro": {
      "fg": "#8839ef"
    },
    "constructor": {
      "fg": "#209fb5"
    },
    "diff.delta": {
      "fg": "#1e66f5"
    },
    "diff.minus": {
      "fg": "#d20f39"
    },
    "diff.plus": {
      "fg": "#40a02b"
    },
    "function": {
      "fg": "#1e66f5"
    },
    "function.builtin": {
      "fg": "#fe640b"
    },
    "function.call": {
      "fg": "#1e66f5"
    },
    "function.macro": {
      "fg": "#179299"
    },
    "function.method": {
      "fg": "#1e66f5"
    },
    "function.method.call": {
      "fg": "#1e66f5"
    },
    "keyword": {
      "fg": "#8839ef"
    },
    "keyword.conditional": {
      "fg": "#8839ef",
      "italic": true
    },
    "keyword.conditional.ternary": {
      "fg": "#04a5e5"
    },
    "keyword.coroutine": {
      "fg": "#8839ef"
    },
    "keyword.debug": {
      "fg": "#8839ef"
    },
    "keyword.directive": {
      "fg": "#ea76cb"
    },
    "keyword.directive.define": {
      "fg": "#ea76cb"
    },
    "keyword.exception": {
      "fg": "#8839ef"
    },
    "keyword.function": {
      "fg": "#8839ef"
    },
    "keyword.import": {
      "fg": "#8839ef"
    },
    "keyword.modifier": {
      "fg": "#8839ef"
    },
    "keyword.operator": {
      "fg": "#04a5e5"
    },
    "keyword.repeat": {
      "fg": "#8839ef"
    },
    "keyword.return": {
      "fg": "#8839ef"
    },
    "keyword.type": {
      "fg": "#8839ef"
    },
    "label": {
      "fg": "#209fb5"
    },
    "markup.heading": {
      "bold": true,
      "fg": "#1e66f5"
    },
    "markup.heading.1": {
      "bold": true,
      "fg": "#1e66f5"
    },
    "markup.heading.2": {
      "bold": true,
      "fg": "#1e66f5"
    },
    "markup.heading.3": {
      "bold": true,
      "fg": "#1e66f5"
    },
    "markup.heading.4": {
      "bold": true,
      "fg": "#1e66f5"
    },
    "markup.heading.5": {
      "bold": true,
      "fg": "#1e66f5"
    },
    "markup.heading.6": {
      "bold": true,
      "fg": "#1e66f5"
    },
    "markup.italic": {
      "fg": "#e64553",
      "italic": true
    },
    "markup.link": {
      "bold": true,
      "fg": "#7287fd"
    },
    "markup.link.label": {
      "fg": "#209fb5"
    },
    "markup.link.url": {
      "fg": "#dc8a78",
      "italic": true,
      "underline": true
    },
    "markup.list": {
      "fg": "#ea76cb"
    },
    "markup.list.checked": {
      "fg": "#40a02b"
    },
    "markup.list.unchecked": {
      "fg": "#8c8fa1"
    },
    "markup.math": {
      "fg": "#1e66f5"
    },
    "markup.quote": {
      "bold": true,
      "fg": "#e64553"
    },
    "markup.raw": {
      "fg": "#179299"
    },
    "markup.raw.block": {
      "fg": "#179299"
    },
    "markup.strikethrough": {
      "fg": "#4c4f69",
      "strikethrough": true
    },
    "markup.strong": {
      "bold": true,
      "fg": "#e64553"
    },
    "markup.underline": {
      "underline": true
    },
    "module": {
      "fg": "#7287fd",
      "italic": true
    },
    "module.builtin": {
      "fg": "#ea76cb"
    },
    "normal": {
      "bg": "#eff1f5",
      "fg": "#4c4f69"
    },
    "number": {
      "fg": "#fe640b"
    },
    "number.float": {
      "fg": "#fe640b"
    },
    "operator": {
      "fg": "#04a5e5"
    },
    "property": {
      "fg": "#7287fd"
    },
    "punctuation.bracket": {
      "fg": "#7c7f93"
    },
    "punctuation.delimiter": {
      "fg": "#7c7f93"
    },
    "punctuation.special": {
      "fg": "#ea76cb"
    },
    "string": {
      "fg": "#40a02b"
    },
    "string.documentation": {
      "fg": "#179299"
    },
    "string.escape": {
      "fg": "#ea76cb"
    },
    "string.regexp": {
      "fg": "#fe640b"
    },
    "string.special": {
      "fg": "#ea76cb"
    },
    "string.special.path": {
      "fg": "#ea76cb"
    },
    "string.special.symbol": {
      "fg": "#dd7878"
    },
    "string.special.url": {
      "fg": "#dc8a78",
      "italic": true,
      "underline": true
    },
    "tag": {
      "fg": "#8839ef"
    },
    "tag.attribute": {
      "fg": "#179299",
      "italic": true
    },
    "tag.builtin": {
      "fg": "#ea76cb"
    },
    "tag.delimiter": {
      "fg": "#04a5e5"
    },
    "type": {
      "fg": "#df8e1d"
    },
    "type.builtin": {
      "fg": "#df8e1d"
    },
    "type.definition": {
      "fg": "#df8e1d"
    },
    "variable": {
      "fg": "#4c4f69"
    },
    "variable.builtin": {
      "fg": "#d20f39"
    },
    "variable.member": {
      "fg": "#7287fd"
    },
    "variable.parameter": {
      "fg": "#e64553"
    },
    "variable.parameter.builtin": {
      "fg": "#ea76cb"
    }
  }
}
