{
  "name": "dawnfox",
  "appearance": "light",
  "highlights": {
    "attribute": {
      "fg": "#ca6e69"
    },
    "attribute.builtin": {
      "fg": "#295e73"
    },
    "boolean": {
      "fg": "#d7827e"
    },
    "character": {
      "fg": "#618774"
    },
    "character.special": {
      "fg": "#295e73"
    },
    "comment": {
      "fg": "#9893a5"
    },
    "comment.documentation": {
      "fg": "#9893a5"
    },
    "constant": {
      "fg": "#ca6e69"
    },
    "constant.builtin": {
      "fg": "#ca6e69"
    },
    "constant.macro": {
      "fg": "#c9709e"
    },
    "constructor": {
      "fg": "#56949f"
    },
    "diff.minus": {
      "fg": "#b4637a"
    },
    "diff.plus": {
      "fg": "#618774"
    },
    "function": {
      "fg": "#295e73"
    },
    "function.builtin": {
      "fg": "#b4637a"
    },
    "function.call": {
      "fg": "#295e73"
    },
    "function.macro": {
      "fg": "#b4637a"
    },
    "function.method": {
      "fg": "#295e73"
    },
    "function.method.call": {
      "fg": "#295e73"
    },
    "keyword": {
      "fg": "#907aa9"
    },
    "keyword.conditional": {
      "fg": "#816b9a"
    },
    "keyword.conditional.ternary": {
      "fg": "#816b9a"
    },
    "keyword.coroutine": {
      "fg": "#907aa9"
    },
    "keyword.debug": {
      "fg": "#907aa9"
    },
    "keyword.directive": {
      "fg": "#907aa9"
    },
    "keyword.directive.define": {
      "fg": "#907aa9"
    },
    "keyword.exception": {
      "fg": "#907aa9"
    },
    "keyword.function": {
      "fg": "#907aa9"
    },
    "keyword.import": {
      "fg": "#c9709e"
    },
    "keyword.modifier": {
      "fg": "#907aa9"
    },
    "keyword.operator": {
      "fg": "#625c87"
    },
    "keyword.repeat": {
      "fg": "#816b9a"
    },
    "keyword.return": {
      "fg": "#b4637a"
    },
    "keyword.type": {
      "fg": "#907aa9"
    },
    "label": {
      "fg": "#816b9a"
    },
    "markup.heading": {
      "bold": true,
      "fg": "#295e73"
    },
    "markup.heading.1": {
      "bold": true,
      "fg": "#295e73"
    },
    "markup.heading.2": {
      "bold": true,
      "fg": "#295e73"
    },
    "markup.heading.3": {
      "bold": true,
      "fg": "#295e73"
    },
    "markup.heading.4": {
      "bold": true,
      "fg": "#295e73"
    },
    "markup.heading.5": {
      "bold": true,
      "fg": "#295e73"
    },
    "markup.heading.6": {
      "bold": true,
      "fg": "#295e73"
    },
    "markup.italic": {
      "italic": true
    },
    "markup.link.label": {
      "fg": "#295e73"
    },
    "markup.raw": {
      "fg": "#56949f",
      "italic": true
    },
    "markup.strikethrough": {
      "fg": "#575279",
      "strikethrough": true
    },
    "markup.strong": {
      "bold": true,
      "fg": "#c26d85"
    },
    "module": {
      "fg": "#50848c"
    },
    "module.builtin": {
      "fg": "#295e73"
    },
    "namespace": {
      "fg": "#50848c"
    },
    "normal": {
      "bg": "#faf4ed",
      "fg": "#575279"
    },
    "number": {
      "fg": "#d7827e"
    },
    "number.float": {
      "fg": "#d7827e"
    },
    "operator": {
      "fg": "#625c87"
    },
    "property": {
      "fg": "#286983"
    },
    "punctuation.bracket": {
      "fg": "#625c87"
    },
    "punctuation.delimiter": {
      "fg": "#625c87"
    },
    "punctuation.special": {
      "fg": "#50848c"
    },
    "string": {
      "fg": "#618774"
    },
    "string.documentation": {
      "fg": "#618774"
    },
    "string.escape": {
      "bold": true,
      "fg": "#dd9024"
    },
    "string.regexp": {
      "fg": "#dd9024"
    },
    "string.special": {
      "fg": "#295e73"
    },
    "string.special.path": {
      "fg": "#295e73"
    },
    "string.special.symbol": {
      "fg": "#295e73"
    },
    "string.special.url": {
      "fg": "#ca6e69",
      "italic": true,
      "underline": true
    },
    "tag": {
      "fg": "#907aa9"
    },
    "tag.attribute": {
      "fg": "#295e73",
      "italic": true
    },
    "tag.delimiter": {
      "fg": "#50848c"
    },
    "type": {
      "fg": "#ea9d34"
    },
    "type.builtin": {
      "fg": "#50848c"
    },
    "type.definition": {
      "fg": "#ea9d34"
    },
    "variable": {
      "fg": "#575279"
    },
    "variable.builtin": {
      "fg": "#b4637a"
    },
    "variable.member": {
      "fg": "#286983"
    },
    "variable.parameter": {
      "fg": "#50848c"
    },
    "variable.parameter.builtin": {
      "fg": "#295e73"
    }
  }
}
